trdr/__init__.py
trdr/conftest.py
trdr/core/__init__.py
trdr/core/bar_provider/__init__.py
trdr/core/bar_provider/base_bar_provider.py
trdr/core/bar_provider/exceptions.py
trdr/core/bar_provider/models.py
trdr/core/bar_provider/yf_bar_provider/__init__.py
trdr/core/bar_provider/yf_bar_provider/test_yf_bar_provider.py
trdr/core/bar_provider/yf_bar_provider/yf_bar_provider.py
trdr/core/broker/__init__.py
trdr/core/broker/base_broker.py
trdr/core/broker/exceptions.py
trdr/core/broker/models.py
trdr/core/broker/test_order_model.py
trdr/core/broker/test_position_model.py
trdr/core/broker/alpaca_broker/README.md
trdr/core/broker/alpaca_broker/__init__.py
trdr/core/broker/alpaca_broker/alpaca_broker.py
trdr/core/broker/mock_broker/__init__.py
trdr/core/broker/mock_broker/mock_broker.py
trdr/core/broker/mock_broker/test_mock_broker.py
trdr/core/broker/mock_broker/test_mock_broker_pdt_validation.py
trdr/core/broker/pdt/README.md
trdr/core/broker/pdt/__init__.py
trdr/core/broker/pdt/base_pdt_strategy.py
trdr/core/broker/pdt/exceptions.py
trdr/core/broker/pdt/models.py
trdr/core/broker/pdt/nun_strategy.py
trdr/core/broker/pdt/test_pdt_evaluation.py
trdr/core/broker/pdt/wiggle_strategy.py
trdr/core/broker/pdt/yolo_strategy.py
trdr/core/security_provider/__init__.py
trdr/core/security_provider/base_security_provider.py
trdr/core/security_provider/models.py
trdr/core/security_provider/security_provider.py
trdr/core/security_provider/test_security_model.py
trdr/core/security_provider/test_security_provider.py
trdr/core/shared/__init__.py
trdr/core/shared/exceptions.py
trdr/core/shared/models.py
trdr/core/trading_context/__init__.py
trdr/core/trading_context/exceptions.py
trdr/core/trading_context/test_trading_context.py
trdr/core/trading_context/trading_context.py
trdr/core/trading_engine/__init__.py
trdr/core/trading_engine/trading_engine.py
trdr/dsl/__init__.py
trdr/dsl/dsl_ast.py
trdr/dsl/dsl_loader.py
trdr/dsl/lexer.py
trdr/dsl/parser.py
trdr/test_utils/__init__.py
trdr-0.0.1.dist-info/METADATA
trdr-0.0.1.dist-info/WHEEL
trdr-0.0.1.dist-info/RECORD
