Metadata-Version: 2.4
Name: trdr
Version: 0.0.1
Summary: Algorithmic trading library
Author-email: developer_jeb <developer_jeb@outlook.com>
Requires-Dist: aiohttp==3.11.11
Requires-Dist: opentelemetry-api==1.30.0
Requires-Dist: opentelemetry-sdk==1.30.0
Requires-Dist: pydantic==2.10.6
Requires-Dist: yfinance==0.2.55
Provides-Extra: dev
Requires-Dist: pytest-asyncio==0.25.2; extra == 'dev'
Requires-Dist: pytest==8.3.4; extra == 'dev'
